flowco/__init__.py
flowco/__main__.py
flowco/assistant/flowco_assistant.py
flowco/assistant/flowco_keys.py
flowco/assistant/trim.py
flowco/builder/assertions.py
flowco/builder/build.py
flowco/builder/cache.py
flowco/builder/check_run.py
flowco/builder/check_syntax.py
flowco/builder/graph_completions.py
flowco/builder/old.py
flowco/builder/pass_config.py
flowco/builder/synthesize.py
flowco/builder/synthesize_kinds.py
flowco/builder/type_ops.py
flowco/builder/unit_tests.py
flowco/cli/__main__.py
flowco/dataflow/check_extended_types.py
flowco/dataflow/checks.py
flowco/dataflow/dfg.py
flowco/dataflow/dfg_update.py
flowco/dataflow/extended_type.py
flowco/dataflow/extended_type_tests.py
flowco/dataflow/function_call.py
flowco/dataflow/parameter.py
flowco/dataflow/phase.py
flowco/dataflow/preconditions.py
flowco/dataflow/schema_markdown.py
flowco/dataflow/tests.py
flowco/dataflow/unittest_editor.py
flowco/llm/assistant.py
flowco/llm/litellm-config.yaml
flowco/llm/message_format.py
flowco/llm/models.py
flowco/llm/test.py
flowco/mxgraph_component/LICENSE
flowco/mxgraph_component/MANIFEST.in
flowco/mxgraph_component/Makefile
flowco/mxgraph_component/README.md
flowco/mxgraph_component/setup.py
flowco/mxgraph_component/e2e/e2e_utils.py
flowco/mxgraph_component/e2e/test_template.py
flowco/mxgraph_component/mxgraph_component/__init__.py
flowco/mxgraph_component/mxgraph_component/frontend/package.json
flowco/mxgraph_component/mxgraph_component/frontend/tsconfig.json
flowco/mxgraph_component/mxgraph_component/frontend/public/bootstrap.min.css
flowco/mxgraph_component/mxgraph_component/frontend/public/connect-hollow.png
flowco/mxgraph_component/mxgraph_component/frontend/public/connect-white.png
flowco/mxgraph_component/mxgraph_component/frontend/public/connect.png
flowco/mxgraph_component/mxgraph_component/frontend/public/connector.gif
flowco/mxgraph_component/mxgraph_component/frontend/public/delete.png
flowco/mxgraph_component/mxgraph_component/frontend/public/edit.png
flowco-0.76.0.dist-info/METADATA
flowco-0.76.0.dist-info/WHEEL
flowco-0.76.0.dist-info/entry_points.txt
flowco-0.76.0.dist-info/licenses/LICENSE
flowco-0.76.0.dist-info/RECORD
