Metadata-Version: 2.4
Name: flowco
Version: 0.76.0
Summary: Flowco a new mixed-initiative system leveraging visual dataflow programming and LLMs to support authoring reliable and robust data analyses.
Project-URL: Homepage, https://github.com/stephenfreund/flowco
Author-email: Stephen Freund <sfreund@williams.edu>, Emery Berger <emery.berger@gmail.com>, Eunice Jun <emjun@cs.ucla.edu>, Brooke Simon <bsimon2000@g.ucla.edu>
License-File: LICENSE
Classifier: License :: OSI Approved :: Apache Software License
Classifier: Operating System :: OS Independent
Classifier: Programming Language :: Python :: 3
Requires-Python: >=3.11
Requires-Dist: black>=24.0
Requires-Dist: deepdiff>=7.0.1
Requires-Dist: flowco-streamlit-flow
Requires-Dist: fsspec
Requires-Dist: google-auth-oauthlib
Requires-Dist: graphviz
Requires-Dist: graphviz>=0.20.3
Requires-Dist: instructor==1.3.1
Requires-Dist: ipykernel>=6.29.4
Requires-Dist: jsonmerge>=1.9.2
Requires-Dist: litellm[proxy]>=1.39.6
Requires-Dist: markdown
Requires-Dist: matplotlib
Requires-Dist: nbclient>=0.10.0
Requires-Dist: nbconvert>=7.16.4
Requires-Dist: nbformat
Requires-Dist: nbformat>=5.1.3
Requires-Dist: numpy
Requires-Dist: openai>=1.72.0
Requires-Dist: pandas
Requires-Dist: pillow>=10.3.0
Requires-Dist: pydantic
Requires-Dist: pytest>=6.2.5
Requires-Dist: pyyaml>=6.0
Requires-Dist: requests
Requires-Dist: s3fs
Requires-Dist: scikit-learn
Requires-Dist: scipy<=1.15.3
Requires-Dist: seaborn
Requires-Dist: statsmodels
Requires-Dist: streamlit-code-editor
Requires-Dist: streamlit-extras>=0.4.7
Requires-Dist: streamlit==1.45.0
Requires-Dist: termcolor>=2.5.0
Requires-Dist: types-pyyaml>=6.0
Provides-Extra: devel
Requires-Dist: build; extra == 'devel'
Requires-Dist: playwright==1.39.0; extra == 'devel'
Requires-Dist: pytest-playwright-snapshot==1.0; extra == 'devel'
Requires-Dist: pytest-rerunfailures==12.0; extra == 'devel'
Requires-Dist: pytest==7.4.0; extra == 'devel'
Requires-Dist: requests==2.31.0; extra == 'devel'
Requires-Dist: selenium; extra == 'devel'
Requires-Dist: webdriver-manager; extra == 'devel'
Requires-Dist: wheel; extra == 'devel'
